amlengine/__init__.py
amlengine/amlhelper.py
amlengine/nuget/aml.engine.2.0.5/lib/net48/Aml.Engine.dll
amlengine/nuget/aml.engine.2.0.5/lib/net5.0/Aml.Engine.dll
amlengine/nuget/aml.engine.2.0.5/lib/net6.0/Aml.Engine.dll
amlengine/nuget/aml.engine.2.0.5/lib/netcoreapp3.1/Aml.Engine.dll
amlengine/nuget/aml.engine.resources.1.0.0/lib/net48/Aml.Engine.Resources.dll
amlengine/nuget/aml.engine.resources.1.0.0/lib/net5.0/Aml.Engine.Resources.dll
amlengine/nuget/aml.engine.resources.1.0.0/lib/net6.0/Aml.Engine.Resources.dll
amlengine/nuget/aml.engine.resources.1.0.0/lib/netcoreapp3.1/Aml.Engine.Resources.dll
amlengine/nuget/aml.engine.services.2.0.3/lib/net48/Aml.Engine.Services.dll
amlengine/nuget/aml.engine.services.2.0.3/lib/net5.0/Aml.Engine.Services.dll
amlengine/nuget/aml.engine.services.2.0.3/lib/net6.0/Aml.Engine.Services.dll
amlengine/nuget/aml.engine.services.2.0.3/lib/netcoreapp3.1/Aml.Engine.Services.dll
amlengine-2.0.5.2.dist-info/LICENSE
amlengine-2.0.5.2.dist-info/METADATA
amlengine-2.0.5.2.dist-info/WHEEL
amlengine-2.0.5.2.dist-info/top_level.txt
amlengine-2.0.5.2.dist-info/RECORD
