Metadata-Version: 2.1
Name: amlengine
Version: 2.0.5.2
Summary: Easy access to the .Net implementation of the AML.Engine (https://github.com/AutomationML/AMLEngine2.1)
Home-page: 
Author: Matthias Freund
Author-email: matth.freund@gmail.com
Project-URL: Docs, https://github.com/AutomationML/AMLEngine2.1
Classifier: Programming Language :: Python :: 3
Classifier: License :: OSI Approved :: MIT License
Classifier: Operating System :: OS Independent
Requires-Python: <3.10,>=3.7
License-File: LICENSE
Requires-Dist: pythonnet
